swarmauri_tool_httploaded/HTTPLoadedTool.py
swarmauri_tool_httploaded/__init__.py
swarmauri_tool_httploaded-0.9.0.dev4.dist-info/LICENSE
swarmauri_tool_httploaded-0.9.0.dev4.dist-info/METADATA
swarmauri_tool_httploaded-0.9.0.dev4.dist-info/WHEEL
swarmauri_tool_httploaded-0.9.0.dev4.dist-info/entry_points.txt
swarmauri_tool_httploaded-0.9.0.dev4.dist-info/RECORD
